MANIFEST.in
README.md
requirements.txt
setup.py
flash_handler/__init__.py
flash_handler/config.py
flash_handler/const.py
flash_handler/error.py
flash_handler/excel_processor.py
flash_handler/file_keeper.py
flash_handler/handler.py
flash_handler/log.py
flash_handler/utils.py
flash_handler.egg-info/PKG-INFO
flash_handler.egg-info/SOURCES.txt
flash_handler.egg-info/dependency_links.txt
flash_handler.egg-info/requires.txt
flash_handler.egg-info/top_level.txt