Metadata-Version: 2.1
Name: flash-handler
Version: 1.0.1
Summary: A simple Excel file handler
Home-page: UNKNOWN
License: UNKNOWN
Platform: UNKNOWN
Classifier: Programming Language :: Python :: 3
